<?xml version="1.1" encoding="UTF-8"?>
<expression:EMFExpression xmi:version="2.0" xmlns:xmi="http://www.omg.org/XMI" xmlns:expression="http:///expression.ecore" id="tMap_1=>" expression="row1.ParticipantType.equals(&quot;INDIVIDUAL&quot;)?row1.MaritalStatus:&quot;AA&quot;">
  <variables name="row1.CustomerID" value="0" talendType="id_Integer"/>
  <variables name="row1.LastName" value="null" talendType="id_String" nullable="true"/>
  <variables name="row1.FirstName" value="null" talendType="id_String" nullable="true"/>
  <variables name="row1.BirthDate" value="null" talendType="id_Date" nullable="true"/>
  <variables name="row1.Gender" value="null" talendType="id_String" nullable="true"/>
  <variables name="row1.ParticipantType" value="null" talendType="id_String" nullable="true"/>
  <variables name="row1.RegionID" value="null" talendType="id_Integer" nullable="true"/>
  <variables name="row1.MaritalStatus" value="null" talendType="id_String" nullable="true"/>
  <variables name="row2.id" value="0" talendType="id_Integer"/>
  <variables name="row2.name" value="null" talendType="id_String" nullable="true"/>
  <variables name="row2.country" value="null" talendType="id_String" nullable="true"/>
  <variables name="row2.State_Code" value="null" talendType="id_String"/>
  <variables name="row2.State" value="null" talendType="id_String" nullable="true"/>
  <variables name="row2.Region" value="null" talendType="id_String" nullable="true"/>
  <variables name="row2.type" value="null" talendType="id_String" nullable="true"/>
  <variables name="row2.latitude" value="null" talendType="id_Float" nullable="true"/>
  <variables name="row2.longitude" value="null" talendType="id_Double" nullable="true"/>
  <variables name="row2.area_code" value="null" talendType="id_Integer" nullable="true"/>
  <variables name="row2.population" value="null" talendType="id_Integer" nullable="true"/>
  <variables name="row2.households" value="null" talendType="id_Integer" nullable="true"/>
  <variables name="row2.median_income" value="null" talendType="id_Integer" nullable="true"/>
  <variables name="row2.land_area" value="null" talendType="id_Integer" nullable="true"/>
  <variables name="row2.water_area" value="null" talendType="id_Integer" nullable="true"/>
  <variables name="row2.time_zone" value="null" talendType="id_String" nullable="true"/>
  <variables name="row4.ProfileID" value="0" talendType="id_Integer"/>
  <variables name="row4.Profile_Code" value="null" talendType="id_String" nullable="true"/>
  <variables name="row4.Type" value="null" talendType="id_String" nullable="true"/>
  <variables name="row4.Sexe" value="null" talendType="id_String" nullable="true"/>
  <variables name="row4.Age" value="null" talendType="id_String" nullable="true"/>
  <variables name="row4.Marital_Status" value="null" talendType="id_String" nullable="true"/>
  <variables name="row4.Change_Freq" value="null" talendType="id_Float" nullable="true"/>
  <variables name="row4.Services_Sat_Rate_On5" value="null" talendType="id_Float" nullable="true"/>
  <variables name="row4.Complain_Sat_Rate" value="null" talendType="id_Float" nullable="true"/>
  <variables name="row4.Res_Time_Days_Expected" value="null" talendType="id_Float" nullable="true"/>
  <variables name="row4.Price_Sat_Rate" value="null" talendType="id_Float" nullable="true"/>
</expression:EMFExpression>
